.gitignore
.travis.yml
LICENSE
MANIFEST.in
README.rst
setup.py
jenkins_job_wrecker/__init__.py
jenkins_job_wrecker/cli.py
jenkins_job_wrecker/helpers.py
jenkins_job_wrecker/registry.py
jenkins_job_wrecker.egg-info/PKG-INFO
jenkins_job_wrecker.egg-info/SOURCES.txt
jenkins_job_wrecker.egg-info/dependency_links.txt
jenkins_job_wrecker.egg-info/entry_points.txt
jenkins_job_wrecker.egg-info/pbr.json
jenkins_job_wrecker.egg-info/requires.txt
jenkins_job_wrecker.egg-info/top_level.txt
jenkins_job_wrecker/modules/__init__.py
jenkins_job_wrecker/modules/base.py
jenkins_job_wrecker/modules/builders.py
jenkins_job_wrecker/modules/buildwrappers.py
jenkins_job_wrecker/modules/handlers.py
jenkins_job_wrecker/modules/lightweight.py
jenkins_job_wrecker/modules/listview.py
jenkins_job_wrecker/modules/properties.py
jenkins_job_wrecker/modules/publishers.py
jenkins_job_wrecker/modules/sandbox.py
jenkins_job_wrecker/modules/scm.py
jenkins_job_wrecker/modules/script.py
jenkins_job_wrecker/modules/scriptpath.py
jenkins_job_wrecker/modules/triggers.py
tests/test_cli.py
tests/test_jjb.py
tests/fixtures/calamari-clients.xml
tests/fixtures/ice-setup.xml
tests/fixtures/non-ascii.xml