Metadata-Version: 1.1
Name: jenkins-job-wrecker
Version: 1.9.0
Summary: convert Jenkins XML to YAML
Home-page: https://github.com/ktdreyer/jenkins-job-wrecker
Author: ken dreyer
Author-email: kdreyer@redhat.com
License: MIT
Keywords: jenkins xml yaml
Platform: UNKNOWN
Classifier: Development Status :: 4 - Beta
Classifier: License :: OSI Approved :: MIT License
Classifier: Operating System :: OS Independent
Classifier: Programming Language :: Python
Classifier: Topic :: Software Development :: Libraries :: Python Modules
